cwlogs_rqid_filter/__init__.py
cwlogs_rqid_filter/__main__.py
cwlogs_rqid_filter/console.py
cwlogs_rqid_filter-0.2.1.dist-info/entry_points.txt
cwlogs_rqid_filter-0.2.1.dist-info/LICENSE
cwlogs_rqid_filter-0.2.1.dist-info/WHEEL
cwlogs_rqid_filter-0.2.1.dist-info/METADATA
cwlogs_rqid_filter-0.2.1.dist-info/RECORD
