Metadata-Version: 2.1
Name: cwlogs-rqid-filter
Version: 0.2.1
Summary: Fetch all log events messages related to requests (by AWS Request ID) that in any message of any event match a custom python regex pattern
Home-page: https://github.com/spascou/cwlogs-rqid-filter
License: MIT
Author: Sylvain Pascou
Author-email: sylvain@pascou.net
Requires-Python: >=3.7,<4.0
Classifier: License :: OSI Approved :: MIT License
Classifier: Programming Language :: Python :: 3
Classifier: Programming Language :: Python :: 3.7
Requires-Dist: boto3 (>=1.9,<2.0)
Requires-Dist: ciso8601 (>=2.1,<3.0)
